CHANGES.txt
MANIFEST.in
README.md
README.txt
setup.py
PGeoREST.egg-info/PKG-INFO
PGeoREST.egg-info/SOURCES.txt
PGeoREST.egg-info/dependency_links.txt
PGeoREST.egg-info/requires.txt
PGeoREST.egg-info/top_level.txt
pgeorest/.gitignore
pgeorest/__init__.py
pgeorest/__init__.pyc
pgeorest/browse_modis.py
pgeorest/browse_modis.pyc
pgeorest/browse_trmm.pyc
pgeorest/browse_trmm1.py
pgeorest/browse_trmm1.pyc
pgeorest/browse_trmm2.py
pgeorest/browse_trmm2.pyc
pgeorest/distribution.py
pgeorest/distribution.pyc
pgeorest/download.py
pgeorest/download.pyc
pgeorest/filesystem.py
pgeorest/filesystem.pyc
pgeorest/main.py
pgeorest/metadata.py
pgeorest/metadata.pyc
pgeorest/schema.py
pgeorest/schema.pyc
pgeorest/search.py
pgeorest/search.pyc
pgeorest/spatialquery.py
pgeorest/spatialquery.pyc
pgeorest/stats.py
pgeorest/stats.pyc
pgeorest/templates/404.html