Metadata-Version: 1.0
Name: PGeoREST
Version: 0.1.11
Summary: PGeoREST module.
Home-page: http://pypi.python.org/pypi/PGeoREST/
Author: Simone Murzilli; Guido Barbaglia
Author-email: geobrickspy@gmail.com
License: LICENSE.txt
Platform: UNKNOWN
